lis2hh12.py
setup.cfg
setup.py
micropython_lis2hh12.egg-info/PKG-INFO
micropython_lis2hh12.egg-info/SOURCES.txt
micropython_lis2hh12.egg-info/dependency_links.txt
micropython_lis2hh12.egg-info/top_level.txt