Metadata-Version: 1.1
Name: micropython-lis2hh12
Version: 0.2.0
Summary: MicroPython I2C driver for LIS2HH12 3-axis accelerometer
Home-page: https://github.com/tuupola/micropython-lis2hh12
Author: Mika Tuupola
Author-email: tuupola@appelsiini.net
License: MIT
Keywords: accelerometer micropython i2c
Platform: UNKNOWN
Classifier: Development Status :: 2 - Pre-Alpha
Classifier: Programming Language :: Python :: Implementation :: MicroPython
Classifier: License :: OSI Approved :: MIT License
